Workbook

Sheet MASTER_DATA
A1: user_id | B1: prompt | C1: status | D1: code | E1: raw_response | F1: created_at | G1: week | H1: is_retrieval | I1: prompt_tokens | J1: response_tokens | K1: total_tokens | L1: prompt_char_length | M1: response_char_length | N1: row_id | O1: prompt_score | P1: response_score | Q1: overall_score | R1: prompt_strengths | S1: prompt_issues | T1: response_strengths | U1: response_issues | V1: prompt_rewrite | W1: response_improvement_suggestions | X1: verdict | Y1: needs_human_review | Z1: model | AA1: raw_json | AB1: evaluation_status | AC1: verdict_num
A2: 2172013 | B2: [MODE:code] Latih parameter akhir theta_final menggunakan data gabungan dan alpha terbaik dari validation curve. ### YOUR CODES HERE ### # Latih model akhir menggunakan alpha terbaik hasil validation curve. theta_final = ... | C2: done | D2: theta_final = train_linear_reg(X_train_final, y_train_final, alpha_vec[np.argmin(error_val)]) | E2: theta_final = train_linear_reg(X_train_final, y_train_final, alpha_vec[np.argmin(error_val)]) | F2: 46119.519 | G2: W8 | H2: 0 | I2: 50 | J2: 22 | K2: 72 | L2: 225 | M2: 93 | N2: 286 | O2: 4 | P2: 4 | Q2: 4 | R2: Clear instructions and context provided. | S2: Could specify the expected format of theta_final more clearly. | T2: Correctly implements the training of the final model. | U2: Lacks explanation of the code and assumptions made. | V2: Latih parameter akhir theta_final menggunakan data gabungan dan alpha terbaik dari validation curve. Tunjukkan hasil dalam format yang jelas. ### YOUR CODES HERE ### | W2: Add comments explaining the code and the rationale behind choosing alpha. | X2: good | Y2: FALSE | Z2: gpt-4o-mini | AA2: {"prompt_score": 4, "response_score": 4, "overall_score": 4, "prompt_strengths": "Clear instructions and context provided.", "prompt_issues": "Could specify the expected format of theta_final more clearly.", "response_strengths": "Correctly implements the training of the final model.", "response_issues": "Lacks explanation of the code and assumptions made.", "prompt_rewrite": "Latih parameter akhir theta_final menggunakan data gabungan dan alpha terbaik dari validation curve. Tunjukkan hasil dalam format yang jelas. ### YOUR CODES HERE ###", "response_improvement_suggestions": "Add comments explaining the code and the rationale behind choosing alpha.", "verdict": "good", "needs_human_review": false} | AB2: ok | AC2: =IF(LOWER(TRIM(X2))="excellent",5, IF(LOWER(TRIM(X2))="good",4, IF(LOWER(TRIM(X2))="fair",3, IF(LOWER(TRIM(X2))="poor",2, IF(LOWER(TRIM(X2))="weak",1,0))))) -> 4 | AD2: =CORREL($O$2:$O$517,$P$2:$P$517) -> 0.62823543
A3: 2172013 | B3: [MODE:code] Lengkapi fungsi poly_features. Yang harus dilakukan: Bentuk fitur polinomial dari derajat 1 sampai derajat p. Jika X berisi satu kolom, maka hasil akhirnya harus berukuran (m, p). def poly_features(X, p): # You need to return the following variable correctly. X_poly = np.zeros((X.size, p)) ### YOUR CODES HERE ### # Diberikan vektor X, kembalikan matriks X_poly # sehingga kolom ke-k berisi X pangkat (k + 1). P = ... X_poly = ... return X_poly | C3: done | D3: import numpy as np def poly_features(X, p): X = np.asarray(X).reshape(-1) X_poly = np.zeros((X.size, p)) P = np.arange(1, p + 1) X_poly = X[:, None] ** P[None, :] return X_poly | E3: ```python import numpy as np def poly_features(X, p): X = np.asarray(X).reshape(-1) X_poly = np.zeros((X.size, p)) P = np.arange(1, p + 1) X_poly = X[:, None] ** P[None, :] return X_poly ``` | F3: 46119.511 | G3: W8 | H3: 0 | I3: 152 | J3: 72 | K3: 224 | L3: 496 | M3: 213 | N3: 2126 | O3: 4 | P3: 4 | Q3: 4 | R3: Clear instructions and specific requirements. | S3: Could provide more context on the input format. | T3: Correct implementation of polynomial feature generation. | U3: Lacks comments explaining the code logic. | V3: Lengkapi fungsi poly_features untuk membentuk fitur polinomial dari derajat 1 sampai p. Input X adalah vektor satu kolom. Kembalikan matriks X_poly berukuran (m, p) dengan kolom ke-k berisi X pangkat (k + 1). | W3: Add comments to explain each step of the code for better clarity. | X3: good | Y3: FALSE | Z3: gpt-4o-mini | AA3: {"prompt_score": 4, "response_score": 4, "overall_score": 4, "prompt_strengths": "Clear instructions and specific requirements.", "prompt_issues": "Could provide more context on the input format.", "response_strengths": "Correct implementation of polynomial feature generation.", "response_issues": "Lacks comments explaining the code logic.", "prompt_rewrite": "Lengkapi fungsi poly_features untuk membentuk fitur polinomial dari derajat 1 sampai p. Input X adalah vektor satu kolom. Kembalikan matriks X_poly berukuran (m, p) dengan kolom ke-k berisi X pangkat (k + 1).", "response_improvement_suggestions": "Add comments to explain each step of the code for better clarity.", "verdict": "good", "needs_human_review": false} | AB3: ok | AC3: =IF(LOWER(TRIM(X3))="excellent",5, IF(LOWER(TRIM(X3))="good",4, IF(LOWER(TRIM(X3))="fair",3, IF(LOWER(TRIM(X3))="poor",2, IF(LOWER(TRIM(X3))="weak",1,0))))) -> 4
A4: 2172013 | B4: [MODE:code] buat code untuk latih grid_serach dari 6000 data pertama pada dataset csv sebelumnya yang sudah dibuat pipeline dengan preprocessing svr | C4: done | D4: import pandas as pd from sklearn.model_selection import GridSearchCV # ====== CONFIG ====== CSV_PATH = "data.csv" # ganti sesuai lokasi file CSV TARGET_COL = "median_house_value" N_TRAIN = 6000 # pakai 6000 baris pertama CV_FOLDS = 3 SCORING = "neg_root_mean_squared_error" # Pastikan variabel ini SUDAH ADA dari kode kamu sebelumnya: # - svr_pipeline (Pipeline: preprocessing + SVR) # - param_grid (dict hyperparameter untuk GridSearchCV) # Contoh key param biasanya: "svr__C", "svr__gamma", "svr__epsilon", "svr__kernel", dll. # ====== LOAD DATA ====== df = pd.read_csv(CSV_PATH) if TARGET_COL not in df.columns: raise ValueError(f"Target column '{TARGET_COL}' tidak ditemukan. Kolom tersedia: {list(df.columns)}") df_train = df.iloc[:N_TRAIN].copy() X_train = df_train.drop(columns=[TARGET_COL]) y_train = df_train[TARGET_COL] # ====== GRID SEARCH TRAINING ====== grid_search = GridSearchCV( estimator=svr_pipeline, param_grid=param_grid, cv=CV_FOLDS, scoring=SCORING, n_jobs=-1, verbose=2, refit=True, ) grid_search.fit(X_train, y_train) print("Best params:", grid_search.best_params_) print("Best CV RMSE:", -grid_search.best_score_) best_model = grid_search.best_estimator_ | E4: ```python import pandas as pd from sklearn.model_selection import GridSearchCV # ====== CONFIG ====== CSV_PATH = "data.csv" # ganti sesuai lokasi file CSV TARGET_COL = "median_house_value" N_TRAIN = 6000 # pakai 6000 baris pertama CV_FOLDS = 3 SCORING = "neg_root_mean_squared_error" # Pastikan variabel ini SUDAH ADA dari kode kamu sebelumnya: # - svr_pipeline (Pipeline: preprocessing + SVR) # - param_grid (dict hyperparameter untuk GridSearchCV) # Contoh key param biasanya: "svr__C", "svr__gamma", "svr__epsilon", "svr__kernel", dll. # ====== LOAD DATA ====== df = pd.read_csv(CSV_PATH) if TARGET_COL not in df.columns: raise ValueError(f"Target column '{TARGET_COL}' tidak ditemukan. Kolom tersedia: {list(df.columns)}") df_train = df.iloc[:N_TRAIN].copy() X_train = df_train.drop(columns=[TARGET_COL]) y_train = df_train[TARGET_COL] # ====== GRID SEARCH TRAINING ====== grid_search = GridSearchCV( estimator=svr_pipeline, param_grid=param_grid, cv=CV_FOLDS, scoring=SCORING, n_jobs=-1, verbose=2, refit=True, ) grid_search.fit(X_train, y_train) print("Best params:", grid_search.best_params_) print("Best CV RMSE:", -grid_search.best_score_) best_model = grid_search.best_estimator_ ``` | F4: 46077.561 | G4: W2 | H4: 0 | I4: 35 | J4: 350 | K4: 385 | L4: 148 | M4: 1263 | N4: 4151 | O4: 4 | P4: 5 | Q4: 5 | R4: Clear and specific about the task. | S4: Could provide more context on the dataset. | T4: Correct, complete, and well-structured code. | U4: None significant. | V4: Buat kode untuk melatih GridSearchCV menggunakan 6000 data pertama dari dataset CSV yang sudah diproses dengan pipeline SVR. | W4: Add comments explaining each step for better clarity. | X4: excellent | Y4: FALSE | Z4: gpt-4o-mini | AA4: {"prompt_score": 4, "response_score": 5, "overall_score": 5, "prompt_strengths": "Clear and specific about the task.", "prompt_issues": "Could provide more context on the dataset.", "response_strengths": "Correct, complete, and well-structured code.", "response_issues": "None significant.", "prompt_rewrite": "Buat kode untuk melatih GridSearchCV menggunakan 6000 data pertama dari dataset CSV yang sudah diproses dengan pipeline SVR.", "response_improvement_suggestions": "Add comments explaining each step for better clarity.", "verdict": "excellent", "needs_human_review": false} | AB4: ok | AC4: =IF(LOWER(TRIM(X4))="excellent",5, IF(LOWER(TRIM(X4))="good",4, IF(LOWER(TRIM(X4))="fair",3, IF(LOWER(TRIM(X4))="poor",2, IF(LOWER(TRIM(X4))="weak",1,0))))) -> 5
A5: 2172013 | B5: [MODE:summary] ini soal kedua Apa tujuan feature scaling? * Mengubah label Membuat semua fitur berada pada skala yang sama Menghapus dataset Menghapus outlier | C5: done | D5: Feature scaling bertujuan membuat semua fitur berada pada skala yang sama agar algoritma yang sensitif terhadap perbedaan skala (misalnya KNN, SVM, regresi) bekerja lebih stabil dan adil. Jadi jawabannya: Membuat semua fitur berada pada skala yang sama. | E5: Feature scaling bertujuan membuat semua fitur berada pada skala yang sama agar algoritma yang sensitif terhadap perbedaan skala (misalnya KNN, SVM, regresi) bekerja lebih stabil dan adil. Jadi jawabannya: Membuat semua fitur berada pada skala yang sama. | F5: 46091.402 | G5: W4 | H5: 0 | I5: 47 | J5: 72 | K5: 119 | L5: 159 | M5: 253 | N5: 4639 | O5: 4 | P5: 5 | Q5: 5 | R5: Clear and specific question about feature scaling. | S5: Could provide more context on feature scaling importance. | T5: Accurate, clear, and directly answers the prompt. | U5: None. | V5: Apa tujuan dari feature scaling dalam machine learning? | W5: None needed; response is already strong. | X5: excellent | Y5: FALSE | Z5: gpt-4o-mini | AA5: {"prompt_score": 4, "response_score": 5, "overall_score": 5, "prompt_strengths": "Clear and specific question about feature scaling.", "prompt_issues": "Could provide more context on feature scaling importance.", "response_strengths": "Accurate, clear, and directly answers the prompt.", "response_issues": "None.", "prompt_rewrite": "Apa tujuan dari feature scaling dalam machine learning?", "response_improvement_suggestions": "None needed; response is already strong.", "verdict": "excellent", "needs_human_review": false} | AB5: ok | AC5: =IF(LOWER(TRIM(X5))="excellent",5, IF(LOWER(TRIM(X5))="good",4, IF(LOWER(TRIM(X5))="fair",3, IF(LOWER(TRIM(X5))="poor",2, IF(LOWER(TRIM(X5))="weak",1,0))))) -> 5
A6: 2172022 | B6: [MODE:code] untuk selanjutnya saya ingin 1.menampilkan score terbaik dari hasil grid_search berdasarkan RMSE. 2.menampilkan best hyperparameter dari hasil grid_search | C6: done | D6: # 1) Score terbaik berdasarkan RMSE (scoring = "neg_root_mean_squared_error") best_rmse = -grid_search.best_score_ print("Best RMSE (CV):", best_rmse) # 2) Best hyperparameter print("Best hyperparameters:", grid_search.best_params_) | E6: ```python # 1) Score terbaik berdasarkan RMSE (scoring = "neg_root_mean_squared_error") best_rmse = -grid_search.best_score_ print("Best RMSE (CV):", best_rmse) # 2) Best hyperparameter print("Best hyperparameters:", grid_search.best_params_) ``` | F6: 46077.544 | G6: W2 | H6: 0 | I6: 43 | J6: 70 | K6: 113 | L6: 167 | M6: 247 | N6: 118 | O6: 4 | P6: 5 | Q6: 4 | R6: Clear and specific about desired outputs. | S6: Could provide more context on the data or model used. | T6: Correct and complete code for the requested tasks. | U6: Could include comments for clarity. | V6: [MODE:code] Tampilkan score terbaik dari grid_search berdasarkan RMSE dan best hyperparameter. Berikan konteks tentang model yang digunakan. | W6: Add comments to explain each part of the code for better clarity. | X6: good | Y6: FALSE | Z6: gpt-4o-mini | AA6: {"prompt_score": 4, "response_score": 5, "overall_score": 4, "prompt_strengths": "Clear and specific about desired outputs.", "prompt_issues": "Could provide more context on the data or model used.", "response_strengths": "Correct and complete code for the requested tasks.", "response_issues": "Could include comments for clarity.", "prompt_rewrite": "[MODE:code] Tampilkan score terbaik dari grid_search berdasarkan RMSE dan best hyperparameter. Berikan konteks tentang model yang digunakan.", "response_improvement_suggestions": "Add comments to explain each part of the code for better clarity.", "verdict": "good", "needs_human_review": false} | AB6: ok | AC6: =IF(LOWER(TRIM(X6))="excellent",5, IF(LOWER(TRIM(X6))="good",4, IF(LOWER(TRIM(X6))="fair",3, IF(LOWER(TRIM(X6))="poor",2, IF(LOWER(TRIM(X6))="weak",1,0))))) -> 4
A7: 2172022 | B7: [MODE:code] housing_labels = pd.read_csv('housing_labels.csv') housing_labels = housing_labels["median_house_value"] | C7: done | D7: import pandas as pd housing_labels = pd.read_csv("housing_labels.csv")["median_house_value"] | E7: ```python import pandas as pd housing_labels = pd.read_csv("housing_labels.csv")["median_house_value"] ``` | F7: 46077.503 | G7: W2 | H7: 0 | I7: 26 | J7: 25 | K7: 51 | L7: 116 | M7: 107 | N7: 815 | O7: 4 | P7: 5 | Q7: 4 | R7: Clear and specific about the task. | S7: Lacks context on the purpose of the code. | T7: Correct and complete code implementation. | U7: Could include comments for clarity. | V7: [MODE:code] Load the median house values from the housing_labels.csv file. | W7: Add comments to explain the code. | X7: good | Y7: FALSE | Z7: gpt-4o-mini | AA7: {"prompt_score": 4, "response_score": 5, "overall_score": 4, "prompt_strengths": "Clear and specific about the task.", "prompt_issues": "Lacks context on the purpose of the code.", "response_strengths": "Correct and complete code implementation.", "response_issues": "Could include comments for clarity.", "prompt_rewrite": "[MODE:code] Load the median house values from the housing_labels.csv file.", "response_improvement_suggestions": "Add comments to explain the code.", "verdict": "good", "needs_human_review": false} | AB7: ok | AC7: =IF(LOWER(TRIM(X7))="excellent",5, IF(LOWER(TRIM(X7))="good",4, IF(LOWER(TRIM(X7))="fair",3, IF(LOWER(TRIM(X7))="poor",2, IF(LOWER(TRIM(X7))="weak",1,0))))) -> 4
A8: 2172022 | B8: [MODE:code] [ASSESSMENT_ID:1771cf8e-0a65-11f1-b762-3e0936ad7efb] [FORCE_GPT:true] [AUTO_FALLBACK:true] sekarang saya ingin membuat model klasifikasi menggunakan LogisticRegression untuk memprediksi pass_fail Pada bagian ini, fitur masukan untuk model klasifikasi harus berasal dari hasil prediksi final_exam_score yang diperoleh pada tahap regresi.jadi alurnya adalah Prediksi final_exam_score terlebih dahulu. lalu Gunakan hasil prediksi tersebut sebagai input untuk LogisticRegression. | C8: done | D8: import numpy as np from sklearn.pipeline import Pipeline from sklearn.compose import ColumnTransformer from sklearn.impute import SimpleImputer from sklearn.preprocessing import OneHotEncoder, StandardScaler from sklearn.linear_model import LinearRegression, LogisticRegression # df harus punya kolom: 'final_exam_score' (target regresi) dan 'pass_fail' (target klasifikasi) # serta fitur lain sebagai input regresi. # Jika Anda sudah punya X_train/X_test/y_reg_train/y_reg_test/y_clf_train/y_clf_test, lewati blok ini. from sklearn.model_selection import train_test_split TARGET_REG = "final_exam_score" TARGET_CLF = "pass_fail" feature_cols = [c for c in df.columns if c not in [TARGET_REG, TARGET_CLF]] X = df[feature_cols] y_reg = df[TARGET_REG] y_clf = df[TARGET_CLF] X_train, X_test, y_reg_train, y_reg_test, y_clf_train, y_clf_test = train_test_split( X, y_reg, y_clf, test_size=0.2, random_state=42, stratify=y_clf ) # --- 1) Regresi: prediksi final_exam_score --- num_cols = X_train.select_dtypes(include="number").columns.tolist() cat_cols = [c for c in X_train.columns if c not in num_cols] preprocess = ColumnTransformer( transformers=[ ("num", Pipeline([("imputer", SimpleImputer(strategy="median")), ("scaler", StandardScaler())]), num_cols), ("cat", Pipeline([("imputer", SimpleImputer(strategy="most_frequent")), ("onehot", OneHotEncoder(handle_unknown="ignore"))]), cat_cols), ], remainder="drop" ) reg_model = Pipeline(steps=[ ("preprocess", preprocess), ("reg", LinearRegression()) ]) reg_model.fit(X_train, y_reg_train) yhat_reg_train = reg_model.predict(X_train).reshape(-1, 1) yhat_reg_test = reg_model.predict(X_test).reshape(-1, 1) # --- 2) Klasifikasi: LogisticRegression dengan input = prediksi regresi --- clf_model = LogisticRegression(max_iter=1000, random_state=42) clf_model.fit(yhat_reg_train, y_clf_train) y_pred = clf_model.predict(yhat_reg_test) y_proba = clf_model.predict_proba(yhat_reg_test)[:, 1] print("Prediksi pass_fail (label):", y_pred[:10]) print("Prediksi pass_fail (proba kelas 1):", y_proba[:10]) | E8: ```python import numpy as np from sklearn.pipeline import Pipeline from sklearn.compose import ColumnTransformer from sklearn.impute import SimpleImputer from sklearn.preprocessing import OneHotEncoder, StandardScaler from sklearn.linear_model import LinearRegression, LogisticRegression # df harus punya kolom: 'final_exam_score' (target regresi) dan 'pass_fail' (target klasifikasi) # serta fitur lain sebagai input regresi. # Jika Anda sudah punya X_train/X_test/y_reg_train/y_reg_test/y_clf_train/y_clf_test, lewati blok ini. from sklearn.model_selection import train_test_split TARGET_REG = "final_exam_score" TARGET_CLF = "pass_fail" feature_cols = [c for c in df.columns if c not in [TARGET_REG, TARGET_CLF]] X = df[feature_cols] y_reg = df[TARGET_REG] y_clf = df[TARGET_CLF] X_train, X_test, y_reg_train, y_reg_test, y_clf_train, y_clf_test = train_test_split( X, y_reg, y_clf, test_size=0.2, random_state=42, stratify=y_clf ) # --- 1) Regresi: prediksi final_exam_score --- num_cols = X_train.select_dtypes(include="number").columns.tolist() cat_cols = [c for c in X_train.columns if c not in num_cols] preprocess = ColumnTransformer( transformers=[ ("num", Pipeline([("imputer", SimpleImputer(strategy="median")), ("scaler", StandardScaler())]), num_cols), ("cat", Pipeline([("imputer", SimpleImputer(strategy="most_frequent")), ("onehot", OneHotEncoder(handle_unknown="ignore"))]), cat_cols), ], remainder="drop" ) reg_model = Pipeline(steps=[ ("preprocess", preprocess), ("reg", LinearRegression()) ]) reg_model.fit(X_train, y_reg_train) yhat_reg_train = reg_model.predict(X_train).reshape(-1, 1) yhat_reg_test = reg_model.predict(X_test).reshape(-1, 1) # --- 2) Klasifikasi: LogisticRegression dengan input = prediksi regresi --- clf_model = LogisticRegression(max_iter=1000, random_state=42) clf_model.fit(yhat_reg_train, y_clf_train) y_pred = clf_model.predict(yhat_reg_test) y_proba = clf_model.predict_proba(yhat_reg_test)[:, 1] print("Prediksi pass_fail (label):", y_pred[:10]) print("Prediksi pass_fail (proba kelas 1):", y_proba[:10]) ``` | F8: 46126.463 | G8: W9 | H8: 0 | I8: 140 | J8: 569 | K8: 709 | L8: 487 | M8: 2164 | N8: 2376 | O8: 4 | P8: 5 | Q8: 4 | R8: Clear instructions and context for model creation. | S8: Could specify the dataset structure more clearly. | T8: Correct implementation of the classification model with clear steps. | U8: Could include comments on the output interpretation. | V8: Buat model klasifikasi menggunakan LogisticRegression untuk memprediksi pass_fail, dengan fitur masukan dari hasil prediksi final_exam_score yang diperoleh dari regresi. Pastikan dataset memiliki kolom 'final_exam_score' dan 'pass_fail'. | W8: Add comments explaining the output predictions and their significance. | X8: good | Y8: FALSE | Z8: gpt-4o-mini | AA8: {"prompt_score": 4, "response_score": 5, "overall_score": 4, "prompt_strengths": "Clear instructions and context for model creation.", "prompt_issues": "Could specify the dataset structure more clearly.", "response_strengths": "Correct implementation of the classification model with clear steps.", "response_issues": "Could include comments on the output interpretation.", "prompt_rewrite": "Buat model klasifikasi menggunakan LogisticRegression untuk memprediksi pass_fail, dengan fitur masukan dari hasil prediksi final_exam_score yang diperoleh dari regresi. Pastikan dataset memiliki kolom 'final_exam_score' dan 'pass_fail'.", "response_improvement_suggestions": "Add comments explaining the output predictions and their significance.", "verdict": "good", "needs_human_review": false} | AB8: ok | AC8: =IF(LOWER(TRIM(X8))="excellent",5, IF(LOWER(TRIM(X8))="good",4, IF(LOWER(TRIM(X8))="fair",3, IF(LOWER(TRIM(X8))="poor",2, IF(LOWER(TRIM(X8))="weak",1,0))))) -> 4
A9: 2172022 | B9: [MODE:code] [ASSESSMENT_ID:1771cf8e-0a65-11f1-b762-3e0936ad7efb] [FORCE_GPT:true] [AUTO_FALLBACK:true] Contoh bonus berikut memakai hasil regresi yang sama, tetapi target klasifikasinya diganti menjadi grade_category untuk klasifikasi multikelas. y_bonus = ... _, _, _, _, y_train_bonus, y_test_bonus = train_test_split( X, y_reg, y_bonus, test_size=0.2, random_state=SEED, stratify=y_bonus ) | C9: done | D9: y_bonus = df["grade_category"] | E9: ```python y_bonus = df["grade_category"] ``` | F9: 46126.48 | G9: W9 | H9: 0 | I9: 133 | J9: 12 | K9: 145 | L9: 397 | M9: 44 | N9: 2535 | O9: 3 | P9: 4 | Q9: 3 | R9: The prompt specifies a clear task related to regression and classification. | S9: Lacks clarity on the expected output format and context for the classification task. | T9: The response is relevant and correctly identifies the target variable. | U9: Incomplete as it does not provide further context or explanation. | V9: Provide a complete example of how to implement the classification using grade_category in a regression context. | W9: Include additional context or steps for implementing the classification task. | X9: fair | Y9: FALSE | Z9: gpt-4o-mini | AA9: {"prompt_score": 3, "response_score": 4, "overall_score": 3, "prompt_strengths": "The prompt specifies a clear task related to regression and classification.", "prompt_issues": "Lacks clarity on the expected output format and context for the classification task.", "response_strengths": "The response is relevant and correctly identifies the target variable.", "response_issues": "Incomplete as it does not provide further context or explanation.", "prompt_rewrite": "Provide a complete example of how to implement the classification using grade_category in a regression context.", "response_improvement_suggestions": "Include additional context or steps for implementing the classification task.", "verdict": "fair", "needs_human_review": false} | AB9: ok | AC9: =IF(LOWER(TRIM(X9))="excellent",5, IF(LOWER(TRIM(X9))="good",4, IF(LOWER(TRIM(X9))="fair",3, IF(LOWER(TRIM(X9))="poor",2, IF(LOWER(TRIM(X9))="weak",1,0))))) -> 3
A10: 2172022 | B10: [MODE:code] untuk selanjutnya bagaimana caranya jika saya ingin melatih grid_search tersebut pada 6000 data pertama | C10: done | D10: # Latih grid_search hanya pada 6000 data pertama (dari data train) # Pastikan X_train dan y_train sudah ada (hasil train_test_split) n = 6000 X_train_6000 = X_train.iloc[:n] if hasattr(X_train, "iloc") else X_train[:n] y_train_6000 = y_train.iloc[:n] if hasattr(y_train, "iloc") else y_train[:n] grid_search.fit(X_train_6000, y_train_6000) print("Best params:", grid_search.best_params_) print("Best CV RMSE:", -grid_search.best_score_) best_model = grid_search.best_estimator_ | E10: ```python # Latih grid_search hanya pada 6000 data pertama (dari data train) # Pastikan X_train dan y_train sudah ada (hasil train_test_split) n = 6000 X_train_6000 = X_train.iloc[:n] if hasattr(X_train, "iloc") else X_train[:n] y_train_6000 = y_train.iloc[:n] if hasattr(y_train, "iloc") else y_train[:n] grid_search.fit(X_train_6000, y_train_6000) print("Best params:", grid_search.best_params_) print("Best CV RMSE:", -grid_search.best_score_) best_model = grid_search.best_estimator_ ``` | F10: 46077.542 | G10: W2 | H10: 0 | I10: 32 | J10: 143 | K10: 175 | L10: 115 | M10: 494 | N10: 3291 | O10: 4 | P10: 5 | Q10: 4 | R10: Clear request for guidance on training with a subset of data. | S10: Could provide more context about the dataset or model. | T10: Directly addresses the prompt with relevant code and explanations. | U10: Could include comments on potential pitfalls or assumptions. | V10: Bagaimana cara melatih grid_search pada 6000 data pertama dari dataset yang telah dibagi? | W10: Add comments on data assumptions and potential issues with subset training. | X10: good | Y10: FALSE | Z10: gpt-4o-mini | AA10: {"prompt_score": 4, "response_score": 5, "overall_score": 4, "prompt_strengths": "Clear request for guidance on training with a subset of data.", "prompt_issues": "Could provide more context about the dataset or model.", "response_strengths": "Directly addresses the prompt with relevant code and explanations.", "response_issues": "Could include comments on potential pitfalls or assumptions.", "prompt_rewrite": "Bagaimana cara melatih grid_search pada 6000 data pertama dari dataset yang telah dibagi?", "response_improvement_suggestions": "Add comments on data assumptions and potential issues with subset training.", "verdict": "good", "needs_human_review": false} | AB10: ok | AC10: =IF(LOWER(TRIM(X10))="excellent",5, IF(LOWER(TRIM(X10))="good",4, IF(LOWER(TRIM(X10))="fair",3, IF(LOWER(TRIM(X10))="poor",2, IF(LOWER(TRIM(X10))="weak",1,0))))) -> 4
A11: 2172022 | B11: [MODE:code] [ASSESSMENT_ID:1771cf8e-0a65-11f1-b762-3e0936ad7efb] [FORCE_GPT:true] [AUTO_FALLBACK:true] # Lengkapi bagian yang diberikan komentar SEED = 42 y_bonus = df["grade_category"] X_train, X_test, y_reg_train, y_reg_test, y_train_bonus, y_test_bonus = train_test_split( X, y_reg, y_bonus, test_size=0.2, random_state=SEED, stratify=y_bonus ) X_train_bonus = y_pred_reg_train X_test_bonus = y_pred_reg_test bonus_model = LogisticRegression(max_iter=2000, random_state=SEED, multi_class="auto") bonus_model.fit(X_train_bonus, y_train_bonus) y_pred_bonus = bonus_model.predict(X_test_bonus) print('Akurasi klasifikasi multikelas grade_category:') print(accuracy_score(y_test_bonus, y_pred_bonus)) ini codingan nya tetaip y_pred_reg_train dan lain lain not difined | C11: done | D11: from sklearn.model_selection import train_test_split from sklearn.preprocessing import LabelEncoder from sklearn.linear_model import LogisticRegression from sklearn.metrics import accuracy_score SEED = 42 # Encode target multikelas agar LogisticRegression bisa dilatih le = LabelEncoder() y_bonus = le.fit_transform(df["grade_category"].astype(str)) # Split (X_train/X_test harus sama dengan yang dipakai untuk prediksi regresi) X_train, X_test, y_reg_train, y_reg_test, y_train_bonus, y_test_bonus = train_test_split( X, y_reg, y_bonus, test_size=0.2, random_state=SEED, stratify=y_bonus ) # Buat dulu prediksi regresi sebagai fitur input klasifikasi y_pred_reg_train = reg_model.predict(X_train).reshape(-1, 1) y_pred_reg_test = reg_model.predict(X_test).reshape(-1, 1) X_train_bonus = y_pred_reg_train X_test_bonus = y_pred_reg_test bonus_model = LogisticRegression(max_iter=2000, random_state=SEED, multi_class="auto") bonus_model.fit(X_train_bonus, y_train_bonus) y_pred_bonus = bonus_model.predict(X_test_bonus) print("Akurasi klasifikasi multikelas grade_category:") print(accuracy_score(y_test_bonus, y_pred_bonus)) | E11: ```python from sklearn.model_selection import train_test_split from sklearn.preprocessing import LabelEncoder from sklearn.linear_model import LogisticRegression from sklearn.metrics import accuracy_score SEED = 42 # Encode target multikelas agar LogisticRegression bisa dilatih le = LabelEncoder() y_bonus = le.fit_transform(df["grade_category"].astype(str)) # Split (X_train/X_test harus sama dengan yang dipakai untuk prediksi regresi) X_train, X_test, y_reg_train, y_reg_test, y_train_bonus, y_test_bonus = train_test_split( X, y_reg, y_bonus, test_size=0.2, random_state=SEED, stratify=y_bonus ) # Buat dulu prediksi regresi sebagai fitur input klasifikasi y_pred_reg_train = reg_model.predict(X_train).reshape(-1, 1) y_pred_reg_test = reg_model.predict(X_test).reshape(-1, 1) X_train_bonus = y_pred_reg_train X_test_bonus = y_pred_reg_test bonus_model = LogisticRegression(max_iter=2000, random_state=SEED, multi_class="auto") bonus_model.fit(X_train_bonus, y_train_bonus) y_pred_bonus = bonus_model.predict(X_test_bonus) print("Akurasi klasifikasi multikelas grade_category:") print(accuracy_score(y_test_bonus, y_pred_bonus)) ``` | F11: 46126.489 | G11: W9 | H11: 0 | I11: 236 | J11: 295 | K11: 531 | L11: 775 | M11: 1151 | N11: 3504 | O11: 3 | P11: 4 | Q11: 4 | R11: The prompt provides a clear coding context and specifies the task. | S11: Lacks clarity on the specific requirements for the missing code. | T11: The response is relevant, correct, and provides a complete solution. | U11: Could improve clarity by adding comments to explain each step. | V11: Lengkapi bagian yang diberikan komentar dengan kode yang tepat untuk mendefinisikan y_pred_reg_train dan y_pred_reg_test. | W11: Add comments to explain the purpose of each code block for better clarity. | X11: good | Y11: FALSE | Z11: gpt-4o-mini | AA11: {"prompt_score": 3, "response_score": 4, "overall_score": 4, "prompt_strengths": "The prompt provides a clear coding context and specifies the task.", "prompt_issues": "Lacks clarity on the specific requirements for the missing code.", "response_strengths": "The response is relevant, correct, and provides a complete solution.", "response_issues": "Could improve clarity by adding comments to explain each step.", "prompt_rewrite": "Lengkapi bagian yang diberikan komentar dengan kode yang tepat untuk mendefinisikan y_pred_reg_train dan y_pred_reg_test.", "response_improvement_suggestions": "Add comments to explain the purpose of each code block for better clarity.", "verdict": "good", "needs_human_review": false} | AB11: ok | AC11: =IF(LOWER(TRIM(X11))="excellent",5, IF(LOWER(TRIM(X11))="good",4, IF(LOWER(TRIM(X11))="fair",3, IF(LOWER(TRIM(X11))="poor",2, IF(LOWER(TRIM(X11))="weak",1,0))))) -> 4
A12: 2172022 | B12: [MODE:code] apa tujuan melatih sebuah model, lalu bagaimana cara menentukan apa yang tepat untuk model tersebut ? | C12: done | D12: Tujuan melatih sebuah model: - Mempelajari pola dari data agar bisa **memprediksi/ mengklasifikasi** data baru (generalization), bukan sekadar “hafal” data latih. - Meminimalkan error/loss pada tugas yang diinginkan (mis. MSE untuk regresi, cross-entropy untuk klasifikasi). - Menghasilkan parameter (bobot/koefisien) yang membuat prediksi seakurat mungkin pada data yang belum pernah dilihat. Cara menentukan apa yang tepat untuk model tersebut: 1) Tentukan jenis masalah & target - Target kontinu → regresi (Linear Regression, Ridge/Lasso, dll) - Target kelas → klasifikasi (Logistic Regression, SVM, Tree, dll) 2) Tentukan metrik evaluasi yang sesuai - Regresi: MSE/MAE/RMSE, R² - Klasifikasi: Accuracy, Precision/Recall, F1, AUC 3) Siapkan pembagian data yang benar - Train/validation/test atau cross-validation - Pastikan tidak ada data leakage 4) Pilih model baseline yang sederhana dulu - Mulai dari model sederhana (mis. linear/logistic) untuk patokan - Lalu bandingkan dengan model yang lebih kompleks bila perlu 5) Cek bias–variance (underfit vs overfit) - Underfit: tambah fitur, model lebih kompleks, kurangi regularisasi - Overfit: tambah data, tambah regularisasi, sederhanakan model, early stopping 6) Tuning hyperparameter dengan validasi - Contoh: λ pada Ridge/Lasso, learning rate, jumlah epoch, depth tree - Pilih yang memberi performa terbaik di validation/cross-validation 7) Pertimbangkan kebutuhan praktis - Interpretabilitas (linear/logistic lebih mudah dijelaskan) - Kecepatan training/inferensi - Ukuran data (data besar → metode iteratif seperti gradient descent lebih cocok) Intinya: “tepat” ditentukan oleh kombinasi **jenis masalah, metrik, hasil validasi, dan kebutuhan praktis** (akurasi vs interpretabilitas vs komputasi). | E12: Tujuan melatih sebuah model: - Mempelajari pola dari data agar bisa **memprediksi/ mengklasifikasi** data baru (generalization), bukan sekadar “hafal” data latih. - Meminimalkan error/loss pada tugas yang diinginkan (mis. MSE untuk regresi, cross-entropy untuk klasifikasi). - Menghasilkan parameter (bobot/koefisien) yang membuat prediksi seakurat mungkin pada data yang belum pernah dilihat. Cara menentukan apa yang tepat untuk model tersebut: 1) Tentukan jenis masalah & target - Target kontinu → regresi (Linear Regression, Ridge/Lasso, dll) - Target kelas → klasifikasi (Logistic Regression, SVM, Tree, dll) 2) Tentukan metrik evaluasi yang sesuai - Regresi: MSE/MAE/RMSE, R² - Klasifikasi: Accuracy, Precision/Recall, F1, AUC 3) Siapkan pembagian data yang benar - Train/validation/test atau cross-validation - Pastikan tidak ada data leakage 4) Pilih model baseline yang sederhana dulu - Mulai dari model sederhana (mis. linear/logistic) untuk patokan - Lalu bandingkan dengan model yang lebih kompleks bila perlu 5) Cek bias–variance (underfit vs overfit) - Underfit: tambah fitur, model lebih kompleks, kurangi regularisasi - Overfit: tambah data, tambah regularisasi, sederhanakan model, early stopping 6) Tuning hyperparameter dengan validasi - Contoh: λ pada Ridge/Lasso, learning rate, jumlah epoch, depth tree - Pilih yang memberi performa terbaik di validation/cross-validation 7) Pertimbangkan kebutuhan praktis - Interpretabilitas (linear/logistic lebih mudah dijelaskan) - Kecepatan training/inferensi - Ukuran data (data besar → metode iteratif seperti gradient descent lebih cocok) Intinya: “tepat” ditentukan oleh kombinasi **jenis masalah, metrik, hasil validasi, dan kebutuhan praktis** (akurasi vs interpretabilitas vs komputasi). | F12: 46126.426 | G12: W9 | H12: 0 | I12: 31 | J12: 529 | K12: 560 | L12: 113 | M12: 1808 | N12: 3588 | O12: 4 | P12: 5 | Q12: 5 | R12: Clear and specific about model training goals. | S12: Could provide more context on the type of model. | T12: Thorough, relevant, and well-structured explanation. | U12: None significant; very comprehensive. | V12: [MODE:code] Apa tujuan melatih model machine learning dan bagaimana cara menentukan model yang tepat untuk masalah tertentu? | W12: Consider adding examples of models for each type of problem. | X12: excellent | Y12: FALSE | Z12: gpt-4o-mini | AA12: {"prompt_score": 4, "response_score": 5, "overall_score": 5, "prompt_strengths": "Clear and specific about model training goals.", "prompt_issues": "Could provide more context on the type of model.", "response_strengths": "Thorough, relevant, and well-structured explanation.", "response_issues": "None significant; very comprehensive.", "prompt_rewrite": "[MODE:code] Apa tujuan melatih model machine learning dan bagaimana cara menentukan model yang tepat untuk masalah tertentu?", "response_improvement_suggestions": "Consider adding examples of models for each type of problem.", "verdict": "excellent", "needs_human_review": false} | AB12: ok | AC12: =IF(LOWER(TRIM(X12))="excellent",5, IF(LOWER(TRIM(X12))="good",4, IF(LOWER(TRIM(X12))="fair",3, IF(LOWER(TRIM(X12))="poor",2, IF(LOWER(TRIM(X12))="weak",1,0))))) -> 5
A13: 2172022 | B13: [MODE:code] NameError Traceback (most recent call last) Cell In[22], line 6 1 # Lengkapi bagian yang diberikan komentar 3 y_bonus = df["grade_category"] 5 X_train, X_test, y_reg_train, y_reg_test, y_train_bonus, y_test_bonus = train_test_split( ----> 6 X, y_reg, y_bonus, test_size=0.2, random_state=SEED, stratify=y_bonus 7 ) 9 X_train_bonus = y_pred_reg_train 10 X_test_bonus = y_pred_reg_test NameError: name 'SEED' is not defined | C13: done | D13: SEED = 42 | E13: ```python SEED = 42 ``` | F13: 46126.484 | G13: W9 | H13: 0 | I13: 152 | J13: 10 | K13: 162 | L13: 505 | M13: 23 | N13: 4434 | O13: 3 | P13: 4 | Q13: 3 | R13: Identifies a specific error in code. | S13: Lacks clarity on what the user should do next. | T13: Provides a clear and relevant solution. | U13: Could include more context or explanation. | V13: Identify the error in the code and suggest how to define 'SEED' properly. | W13: Explain why 'SEED' is set to 42 and its significance. | X13: fair | Y13: FALSE | Z13: gpt-4o-mini | AA13: {"prompt_score": 3, "response_score": 4, "overall_score": 3, "prompt_strengths": "Identifies a specific error in code.", "prompt_issues": "Lacks clarity on what the user should do next.", "response_strengths": "Provides a clear and relevant solution.", "response_issues": "Could include more context or explanation.", "prompt_rewrite": "Identify the error in the code and suggest how to define 'SEED' properly.", "response_improvement_suggestions": "Explain why 'SEED' is set to 42 and its significance.", "verdict": "fair", "needs_human_review": false} | AB13: ok | AC13: =IF(LOWER(TRIM(X13))="excellent",5, IF(LOWER(TRIM(X13))="good",4, IF(LOWER(TRIM(X13))="fair",3, IF(LOWER(TRIM(X13))="poor",2, IF(LOWER(TRIM(X13))="weak",1,0))))) -> 3
A14: 2172022 | B14: [MODE:code] apakah df.info() menunjukan dataset memiliki berapa baris dan berapa kolom, bagaimana cara menampilkan dataset memiliki berapa baris dan kolom? | C14: done | D14: # df.info() menampilkan ringkasan termasuk jumlah baris (entries) dan jumlah kolom (Data columns), # tapi cara paling langsung untuk menampilkan jumlah baris & kolom adalah: print(df.shape) # (jumlah_baris, jumlah_kolom) rows, cols = df.shape print("Jumlah baris:", rows) print("Jumlah kolom:", cols) # Alternatif: print("Jumlah baris:", len(df)) # baris print("Jumlah kolom:", df.shape[1]) # kolom | E14: ```python # df.info() menampilkan ringkasan termasuk jumlah baris (entries) dan jumlah kolom (Data columns), # tapi cara paling langsung untuk menampilkan jumlah baris & kolom adalah: print(df.shape) # (jumlah_baris, jumlah_kolom) rows, cols = df.shape print("Jumlah baris:", rows) print("Jumlah kolom:", cols) # Alternatif: print("Jumlah baris:", len(df)) # baris print("Jumlah kolom:", df.shape[1]) # kolom ``` | F14: 46126.445 | G14: W9 | H14: 0 | I14: 41 | J14: 125 | K14: 166 | L14: 155 | M14: 443 | N14: 4665 | O14: 4 | P14: 5 | Q14: 5 | R14: Clear and specific question about dataset dimensions. | S14: Could provide more context on the dataset type. | T14: Correct, complete, and clear explanation with code examples. | U14: None significant. | V14: Apa df.info() menunjukkan jumlah baris dan kolom dalam dataset? Bagaimana cara menampilkan jumlah baris dan kolom tersebut? | W14: None needed; response is already comprehensive. | X14: excellent | Y14: FALSE | Z14: gpt-4o-mini | AA14: {"prompt_score": 4, "response_score": 5, "overall_score": 5, "prompt_strengths": "Clear and specific question about dataset dimensions.", "prompt_issues": "Could provide more context on the dataset type.", "response_strengths": "Correct, complete, and clear explanation with code examples.", "response_issues": "None significant.", "prompt_rewrite": "Apa df.info() menunjukkan jumlah baris dan kolom dalam dataset? Bagaimana cara menampilkan jumlah baris dan kolom tersebut?", "response_improvement_suggestions": "None needed; response is already comprehensive.", "verdict": "excellent", "needs_human_review": false} | AB14: ok | AC14: =IF(LOWER(TRIM(X14))="excellent",5, IF(LOWER(TRIM(X14))="good",4, IF(LOWER(TRIM(X14))="fair",3, IF(LOWER(TRIM(X14))="poor",2, IF(LOWER(TRIM(X14))="weak",1,0))))) -> 5
... A517: 2472901 | B517: [MODE:summary] berikan jawaban dari 2 pertanyaan ini Fungsi hipotesis terhadap linear regression * sigmoid θ·x + bias softmax exponential λ besar pada Lasso * Random Beberapa nol Tidak berubah Fitur besar berikan jawaban singkat dan padat | C517: done | D517: - Fungsi hipotesis linear regression: θ·x + bias - λ besar pada Lasso: Beberapa nol | E517: - Fungsi hipotesis linear regression: θ·x + bias - λ besar pada Lasso: Beberapa nol | F517: 46126.416 | G517: W9 | H517: 0 | I517: 70 | J517: 28 | K517: 98 | L517: 239 | M517: 85 | N517: 4759 | O517: 3 | P517: 4 | Q517: 3 | R517: Addresses specific topics in regression. | S517: Lacks clarity and structure; confusing phrasing. | T517: Concise and relevant answers. | U517: Lacks detail and explanation. | V517: Berikan jawaban singkat untuk dua pertanyaan: Apa fungsi hipotesis dalam regresi linear? Apa dampak dari λ besar pada Lasso? | W517: Expand on the explanations for better understanding. | X517: fair | Y517: FALSE | Z517: gpt-4o-mini | AA517: {"prompt_score": 3, "response_score": 4, "overall_score": 3, "prompt_strengths": "Addresses specific topics in regression.", "prompt_issues": "Lacks clarity and structure; confusing phrasing.", "response_strengths": "Concise and relevant answers.", "response_issues": "Lacks detail and explanation.", "prompt_rewrite": "Berikan jawaban singkat untuk dua pertanyaan: Apa fungsi hipotesis dalam regresi linear? Apa dampak dari λ besar pada Lasso?", "response_improvement_suggestions": "Expand on the explanations for better understanding.", "verdict": "fair", "needs_human_review": false} | AB517: ok | AC517: =IF(LOWER(TRIM(X517))="excellent",5, IF(LOWER(TRIM(X517))="good",4, IF(LOWER(TRIM(X517))="fair",3, IF(LOWER(TRIM(X517))="poor",2, IF(LOWER(TRIM(X517))="weak",1,0))))) -> 3
AC518: =IF(LOWER(TRIM(X518))="excellent",5, IF(LOWER(TRIM(X518))="good",4, IF(LOWER(TRIM(X518))="fair",3, IF(LOWER(TRIM(X518))="poor",2, IF(LOWER(TRIM(X518))="weak",1,0))))) -> 0
AC519: =IF(LOWER(TRIM(X519))="excellent",5, IF(LOWER(TRIM(X519))="good",4, IF(LOWER(TRIM(X519))="fair",3, IF(LOWER(TRIM(X519))="poor",2, IF(LOWER(TRIM(X519))="weak",1,0))))) -> 0
AC520: =IF(LOWER(TRIM(X520))="excellent",5, IF(LOWER(TRIM(X520))="good",4, IF(LOWER(TRIM(X520))="fair",3, IF(LOWER(TRIM(X520))="poor",2, IF(LOWER(TRIM(X520))="weak",1,0))))) -> 0
AC521: =IF(LOWER(TRIM(X521))="excellent",5, IF(LOWER(TRIM(X521))="good",4, IF(LOWER(TRIM(X521))="fair",3, IF(LOWER(TRIM(X521))="poor",2, IF(LOWER(TRIM(X521))="weak",1,0))))) -> 0
AC522: =IF(LOWER(TRIM(X522))="excellent",5, IF(LOWER(TRIM(X522))="good",4, IF(LOWER(TRIM(X522))="fair",3, IF(LOWER(TRIM(X522))="poor",2, IF(LOWER(TRIM(X522))="weak",1,0))))) -> 0
AC523: =IF(LOWER(TRIM(X523))="excellent",5, IF(LOWER(TRIM(X523))="good",4, IF(LOWER(TRIM(X523))="fair",3, IF(LOWER(TRIM(X523))="poor",2, IF(LOWER(TRIM(X523))="weak",1,0))))) -> 0
AC524: =IF(LOWER(TRIM(X524))="excellent",5, IF(LOWER(TRIM(X524))="good",4, IF(LOWER(TRIM(X524))="fair",3, IF(LOWER(TRIM(X524))="poor",2, IF(LOWER(TRIM(X524))="weak",1,0))))) -> 0
AC525: =IF(LOWER(TRIM(X525))="excellent",5, IF(LOWER(TRIM(X525))="good",4, IF(LOWER(TRIM(X525))="fair",3, IF(LOWER(TRIM(X525))="poor",2, IF(LOWER(TRIM(X525))="weak",1,0))))) -> 0
AC526: =IF(LOWER(TRIM(X526))="excellent",5, IF(LOWER(TRIM(X526))="good",4, IF(LOWER(TRIM(X526))="fair",3, IF(LOWER(TRIM(X526))="poor",2, IF(LOWER(TRIM(X526))="weak",1,0))))) -> 0
AC527: =IF(LOWER(TRIM(X527))="excellent",5, IF(LOWER(TRIM(X527))="good",4, IF(LOWER(TRIM(X527))="fair",3, IF(LOWER(TRIM(X527))="poor",2, IF(LOWER(TRIM(X527))="weak",1,0))))) -> 0
AC528: =IF(LOWER(TRIM(X528))="excellent",5, IF(LOWER(TRIM(X528))="good",4, IF(LOWER(TRIM(X528))="fair",3, IF(LOWER(TRIM(X528))="poor",2, IF(LOWER(TRIM(X528))="weak",1,0))))) -> 0
AC529: =IF(LOWER(TRIM(X529))="excellent",5, IF(LOWER(TRIM(X529))="good",4, IF(LOWER(TRIM(X529))="fair",3, IF(LOWER(TRIM(X529))="poor",2, IF(LOWER(TRIM(X529))="weak",1,0))))) -> 0
... AC536: =IF(LOWER(TRIM(X536))="excellent",5, IF(LOWER(TRIM(X536))="good",4, IF(LOWER(TRIM(X536))="fair",3, IF(LOWER(TRIM(X536))="poor",2, IF(LOWER(TRIM(X536))="weak",1,0))))) -> 0

Sheet System Efficiency
A1: TOTAL TOKEN (RETRIEVAL + CHATGPT) | L1: TOTAL TOKEN (RETRIEVAL ONLY) | W1: TOTAL TOKEN (CHATGPT ONLY)
A3: Row Labels | B3: W2 | C3: W3 | D3: W4 | E3: W5 | F3: W7 | G3: W8 | H3: W9 | I3: Grand Total | L3: Row Labels | M3: W2 | N3: W3 | O3: W4 | P3: W5 | Q3: W7 | R3: W8 | S3: W9 | T3: Grand Total | W3: Row Labels | X3: W2 | Y3: W3 | Z3: W4 | AA3: W5 | AB3: W7 | AC3: W8 | AD3: W9 | AE3: Grand Total
A4: 2172013 | B4: 6003 | C4: 590 | D4: 2906 | E4: 1042 | F4: 1541 | G4: 1679 | H4: 1437 | I4: 15198 | L4: 2172013 | M4: 5618 | N4: 590 | O4: 2787 | P4: 1042 | Q4: 1541 | R4: 1383 | S4: 1437 | T4: =SUM(M4:S4) -> 14398 | W4: 2172013 | X4: 385 | Y4: 0 | Z4: 119 | AA4: 0 | AB4: 0 | AC4: 296 | AD4: 0 | AE4: 800
A5: 2172022 | B5: 2102 | C5: 0 | D5: 0 | E5: 0 | F5: 0 | G5: 799 | H5: 11849 | I5: 14750 | L5: 2172022 | M5: 1763 | N5: 0 | O5: 0 | P5: 0 | Q5: 0 | R5: 799 | S5: 9576 | T5: =SUM(M5:S5) -> 12138 | W5: 2172022 | X5: 339 | Y5: 0 | Z5: 0 | AA5: 0 | AB5: 0 | AC5: 0 | AD5: 2273 | AE5: 2612
A6: 2172025 | B6: 2357 | C6: 2817 | D6: 2733 | E6: 7598 | F6: 5231 | G6: 0 | H6: 22291 | I6: 43027 | L6: 2172025 | M6: 2002 | N6: 1883 | O6: 1785 | P6: 5435 | Q6: 4195 | R6: 0 | S6: 19425 | T6: =SUM(M6:S6) -> 34725 | W6: 2172025 | X6: 355 | Y6: 934 | Z6: 948 | AA6: 2163 | AB6: 1036 | AC6: 0 | AD6: 2866 | AE6: 8302
A7: 2272017 | B7: 0 | C7: 0 | D7: 297 | E7: 0 | F7: 1307 | G7: 0 | H7: 0 | I7: 1604 | L7: 2272017 | M7: 0 | N7: 0 | O7: 167 | P7: 0 | Q7: 1307 | R7: 0 | S7: 0 | T7: =SUM(M7:S7) -> 1474 | W7: 2272017 | X7: 0 | Y7: 0 | Z7: 130 | AA7: 0 | AB7: 0 | AC7: 0 | AD7: 0 | AE7: 130
A8: 2372004 | B8: 1544 | C8: 71 | D8: 251 | E8: 1089 | F8: 3446 | G8: 0 | H8: 4119 | I8: 10520 | L8: 2372004 | M8: 1544 | N8: 71 | O8: 251 | P8: 779 | Q8: 3152 | R8: 0 | S8: 4033 | T8: =SUM(M8:S8) -> 9830 | W8: 2372004 | X8: 0 | Y8: 0 | Z8: 0 | AA8: 310 | AB8: 294 | AC8: 0 | AD8: 86 | AE8: 690
A9: 2372006 | B9: 2310 | C9: 1201 | D9: 0 | E9: 0 | F9: 1737 | G9: 1428 | H9: 3304 | I9: 9980 | L9: 2372006 | M9: 1250 | N9: 1201 | O9: 0 | P9: 0 | Q9: 1304 | R9: 1428 | S9: 2165 | T9: =SUM(M9:S9) -> 7348 | W9: 2372006 | X9: 1060 | Y9: 0 | Z9: 0 | AA9: 0 | AB9: 433 | AC9: 0 | AD9: 1139 | AE9: 2632
A10: 2372012 | B10: 2313 | C10: 409 | D10: 901 | E10: 335 | F10: 0 | G10: 0 | H10: 0 | I10: 3958 | L10: 2372012 | M10: 1639 | N10: 0 | O10: 614 | P10: 89 | Q10: 0 | R10: 0 | S10: 0 | T10: =SUM(M10:S10) -> 2342 | W10: 2372012 | X10: 674 | Y10: 409 | Z10: 287 | AA10: 246 | AB10: 0 | AC10: 0 | AD10: 0 | AE10: 1616
A11: 2372017 | B11: 1934 | C11: 1284 | D11: 820 | E11: 0 | F11: 526 | G11: 0 | H11: 0 | I11: 4564 | L11: 2372017 | M11: 599 | N11: 966 | O11: 820 | P11: 0 | Q11: 526 | R11: 0 | S11: 0 | T11: =SUM(M11:S11) -> 2911 | W11: 2372017 | X11: 1335 | Y11: 318 | Z11: 0 | AA11: 0 | AB11: 0 | AC11: 0 | AD11: 0 | AE11: 1653
A12: 2372019 | B12: 2292 | C12: 0 | D12: 860 | E12: 0 | F12: 0 | G12: 694 | H12: 4281 | I12: 8127 | L12: 2372019 | M12: 1826 | N12: 0 | O12: 769 | P12: 0 | Q12: 0 | R12: 694 | S12: 2911 | T12: =SUM(M12:S12) -> 6200 | W12: 2372019 | X12: 466 | Y12: 0 | Z12: 91 | AA12: 0 | AB12: 0 | AC12: 0 | AD12: 1370 | AE12: 1927
A13: 2372022 | B13: 1765 | C13: 1512 | D13: 0 | E13: 0 | F13: 106 | G13: 72 | H13: 0 | I13: 3455 | L13: 2372022 | M13: 1706 | N13: 1050 | O13: 0 | P13: 0 | Q13: 106 | R13: 72 | S13: 0 | T13: =SUM(M13:S13) -> 2934 | W13: 2372022 | X13: 59 | Y13: 462 | Z13: 0 | AA13: 0 | AB13: 0 | AC13: 0 | AD13: 0 | AE13: 521
A14: 2372027 | B14: 2547 | C14: 1429 | D14: 0 | E14: 2456 | F14: 0 | G14: 0 | H14: 8585 | I14: 15017 | L14: 2372027 | M14: 2547 | N14: 1361 | O14: 0 | P14: 1716 | Q14: 0 | R14: 0 | S14: 8268 | T14: =SUM(M14:S14) -> 13892 | W14: 2372027 | X14: 0 | Y14: 68 | Z14: 0 | AA14: 740 | AB14: 0 | AC14: 0 | AD14: 317 | AE14: 1125
A15: 2372028 | B15: 2644 | C15: 4147 | D15: 0 | E15: 0 | F15: 946 | G15: 1570 | H15: 10453 | I15: 19760 | L15: 2372028 | M15: 2644 | N15: 3022 | O15: 0 | P15: 0 | Q15: 383 | R15: 425 | S15: 8179 | T15: =SUM(M15:S15) -> 14653 | W15: 2372028 | X15: 0 | Y15: 1125 | Z15: 0 | AA15: 0 | AB15: 563 | AC15: 1145 | AD15: 2274 | AE15: 5107
... A70: 2472901 | B70: 3556 | C70: 1102 | D70: 1703 | E70: 0 | F70: 0 | G70: 0 | H70: 1835 | I70: 8196 | L70: 2472901 | M70: 3556 | N70: 951 | O70: 1703 | P70: 0 | Q70: 0 | R70: 0 | S70: 1482 | T70: =SUM(M70:S70) -> 7692 | W70: 2472061 | X70: 0 | Y70: 0 | Z70: 0 | AA70: 0 | AB70: 0 | AC70: 0 | AD70: 0 | AE70: 0
A71: Grand Total | B71: 143666 | C71: 87861 | D71: 179906 | E71: 124380 | F71: 71810 | G71: 92208 | H71: 394989 | I71: 1094820 | L71: Grand Total | M71: =SUM(M4:M70) -> 109085 | N71: =SUM(N4:N70) -> 70835 | O71: =SUM(O4:O70) -> 144443 | P71: =SUM(P4:P70) -> 98225 | Q71: =SUM(Q4:Q70) -> 59995 | R71: =SUM(R4:R70) -> 74258 | S71: =SUM(S4:S70) -> 311697 | T71: =SUM(T4:T70) -> 868538 | W71: Grand Total | X71: 34581 | Y71: 17026 | Z71: 35463 | AA71: 26155 | AB71: 11815 | AC71: 17950 | AD71: 83292 | AE71: 226282
A74: Total S-SPARC | B74: 1094820
A75: Hanya ChatGPT | B75: 226282
A76: Inferensi hanya | B76: =B75/B74 -> 0.2066842
A77: hemat | B77: =1-B76 -> 0.7933158

Sheet User Quality
A1: Row Labels | B1: Sum of total_tokens | C1: Average of verdict_num | D1: Average of response_score | E1: Average of prompt_score | F1: Efficiency Score
A2: 2372062 | B2: 308 | C2: 4.5 | D2: 5 | E2: 4 | F2: =C2/LOG(B2) -> 1.8082814
A3: 2472052 | B3: 908 | C3: 5 | D3: 5 | E3: 4 | F3: =C3/LOG(B3) -> 1.6902822
A4: 2472037 | B4: 265 | C4: 4 | D4: 4.75 | E4: 3.75 | F4: =C4/LOG(B4) -> 1.6506786
A5: 2472003 | B5: 652 | C5: 4.5 | D5: 5 | E5: 4 | F5: =C5/LOG(B5) -> 1.5990064
A6: 2472030 | B6: 709 | C6: 4.5 | D6: 4.5 | E6: 4 | F6: =C6/LOG(B6) -> 1.5785894
A7: 2172013 | B7: 800 | C7: 4.5 | D7: 4.5 | E7: 4 | F7: =C7/LOG(B7) -> 1.5500725
A8: 2272017 | B8: 130 | C8: 3 | D8: 4 | E8: 3 | F8: =C8/LOG(B8) -> 1.4191487
A9: 2472012 | B9: 2097 | C9: 4.6666667 | D9: 4.8333333 | E9: 3.8333333 | F9: =C9/LOG(B9) -> 1.4049461
A10: 2372063 | B10: 1758 | C10: 4.5 | D10: 4.5 | E10: 3.5 | F10: =C10/LOG(B10) -> 1.3867408
A11: 2472026 | B11: 356 | C11: 3.5 | D11: 4 | E11: 3 | F11: =C11/LOG(B11) -> 1.371769
A12: 2472001 | B12: 1790 | C12: 4.4545455 | D12: 4.6363636 | E12: 3.7272727 | F12: =C12/LOG(B12) -> 1.3694272
A13: 2372027 | B13: 1125 | C13: 4.1666667 | D13: 4.3333333 | E13: 3.5 | F13: =C13/LOG(B13) -> 1.3656042
... A66: 2472013 | B66: 1145 | C66: 1 | D66: 2 | E66: 3 | F66: =C66/LOG(B66) -> 0.32692501

Sheet Trends
A1: Row Labels | B1: Average of prompt_score | C1: Average of response_score | D1: Average of verdict_num
A2: W2 | B2: 3.5588235 | C2: 4.6029412 | D2: 4.2058824
A3: W3 | B3: 3.7 | C3: 4.74 | D3: 4.3
A4: W4 | B4: 3.7822581 | C4: 4.6854839 | D4: 4.2983871
A5: W5 | B5: 3.7386364 | C5: 4.6818182 | D5: 4.3068182
A6: W7 | B6: 3.9285714 | C6: 4.8571429 | D6: 4.5714286
A7: W8 | B7: 3.78125 | C7: 4.5625 | D7: 4.40625
A8: W9 | B8: 3.6349206 | C8: 4.3015873 | D8: 4.0873016
A9: Grand Total | B9: 3.7093023 | C9: 4.5872093 | D9: 4.2577519

Sheet Prompt Response Correl
A3: Row Labels | B3: Average of verdict_num | C3: Average of total_tokens | D3: Average of prompt_score | E3: Average of response_score
A4: 2172013 | B4: 4.5 | C4: 200 | D4: 4 | E4: 4.5
A5: 2172022 | B5: 4 | C5: 290.22222 | D5: 3.6666667 | E5: 4.6666667
A6: 2172025 | B6: 3.8947368 | C6: 436.94737 | D6: 3.5789474 | E6: 4.4210526
A7: 2272017 | B7: 3 | C7: 130 | D7: 3 | E7: 4
A8: 2372004 | B8: 3.5 | C8: 115 | D8: 3.1666667 | E8: 4.1666667
A9: 2372006 | B9: 4.25 | C9: 658 | D9: 3.75 | E9: 4
A10: 2372012 | B10: 3.875 | C10: 202 | D10: 3.625 | E10: 4
A11: 2372017 | B11: 4.3333333 | C11: 551 | D11: 3.3333333 | E11: 4.3333333
A12: 2372019 | B12: 3.6 | C12: 385.4 | D12: 3.2 | E12: 4.4
A13: 2372022 | B13: 3.5 | C13: 260.5 | D13: 3 | E13: 4.5
A14: 2372027 | B14: 4.1666667 | C14: 187.5 | D14: 3.5 | E14: 4.3333333
A15: 2372028 | B15: 4.3333333 | C15: 567.44444 | D15: 3.5555556 | E15: 4.6666667
... A68: 2472901 | B68: 3.6 | C68: 100.8 | D68: 3.2 | E68: 4
A69: Grand Total | B69: 4.2577519 | C69: 438.53101 | D69: 3.7093023 | E69: 4.5872093
A72: Apakah prompt bagus → response bagus? | B72: =CORREL($D$4:$D$68, E4:E68) -> 0.67371116 | C72: Prompt engineering memang berdampak langsung ke kualitas output LLM.
A73: Apakah prompt bagus → verdict bagus? | B73: =CORREL(D4:D68,B4:B68) -> 0.75028601 | C73: Kualitas prompt merupakan faktor dominan dalam menentukan kualitas keseluruhan interaksi.
A74: Apakah prompt bagus → lebih hemat token? | B74: =CORREL(D4:D68,C4:C68) -> 0.10888261 | C74: Kualitas prompt tidak menjamin efisiensi token.
A76: Prompt bagus → lebih detail → response lebih panjang
A77: Jadi kualitas naik, tapi token tidak turun

Sheet Regresi
A1: username | B1: avg_verdict_num | C1: total_tokens | D1: chatgpt_token | E1: ratio
A2: 2172013 | B2: 4.5 | C2: =VLOOKUP(A2,'System Efficiency'!$A$4:$I$71,9,0) -> 15198 | D2: =VLOOKUP(A2,'System Efficiency'!$W$4:$AE$71,9,0) -> 800 | E2: =D2/C2 -> 0.052638505
A3: 2172022 | B3: 4 | C3: =VLOOKUP(A3,'System Efficiency'!$A$4:$I$71,9,0) -> 14750 | D3: =VLOOKUP(A3,'System Efficiency'!$W$4:$AE$71,9,0) -> 2612 | E3: =D3/C3 -> 0.17708475
A4: 2172025 | B4: 3.8947368 | C4: =VLOOKUP(A4,'System Efficiency'!$A$4:$I$71,9,0) -> 43027 | D4: =VLOOKUP(A4,'System Efficiency'!$W$4:$AE$71,9,0) -> 8302 | E4: =D4/C4 -> 0.19294861
A5: 2272017 | B5: 3 | C5: =VLOOKUP(A5,'System Efficiency'!$A$4:$I$71,9,0) -> 1604 | D5: =VLOOKUP(A5,'System Efficiency'!$W$4:$AE$71,9,0) -> 130 | E5: =D5/C5 -> 0.081047382
A6: 2372004 | B6: 3.5 | C6: =VLOOKUP(A6,'System Efficiency'!$A$4:$I$71,9,0) -> 10520 | D6: =VLOOKUP(A6,'System Efficiency'!$W$4:$AE$71,9,0) -> 690 | E6: =D6/C6 -> 0.065589354
A7: 2372006 | B7: 4.25 | C7: =VLOOKUP(A7,'System Efficiency'!$A$4:$I$71,9,0) -> 9980 | D7: =VLOOKUP(A7,'System Efficiency'!$W$4:$AE$71,9,0) -> 2632 | E7: =D7/C7 -> 0.26372745
A8: 2372012 | B8: 3.875 | C8: =VLOOKUP(A8,'System Efficiency'!$A$4:$I$71,9,0) -> 3958 | D8: =VLOOKUP(A8,'System Efficiency'!$W$4:$AE$71,9,0) -> 1616 | E8: =D8/C8 -> 0.40828701
A9: 2372017 | B9: 4.3333333 | C9: =VLOOKUP(A9,'System Efficiency'!$A$4:$I$71,9,0) -> 4564 | D9: =VLOOKUP(A9,'System Efficiency'!$W$4:$AE$71,9,0) -> 1653 | E9: =D9/C9 -> 0.3621823
A10: 2372019 | B10: 3.6 | C10: =VLOOKUP(A10,'System Efficiency'!$A$4:$I$71,9,0) -> 8127 | D10: =VLOOKUP(A10,'System Efficiency'!$W$4:$AE$71,9,0) -> 1927 | E10: =D10/C10 -> 0.23711087
A11: 2372022 | B11: 3.5 | C11: =VLOOKUP(A11,'System Efficiency'!$A$4:$I$71,9,0) -> 3455 | D11: =VLOOKUP(A11,'System Efficiency'!$W$4:$AE$71,9,0) -> 521 | E11: =D11/C11 -> 0.15079595
A12: 2372027 | B12: 4.1666667 | C12: =VLOOKUP(A12,'System Efficiency'!$A$4:$I$71,9,0) -> 15017 | D12: =VLOOKUP(A12,'System Efficiency'!$W$4:$AE$71,9,0) -> 1125 | E12: =D12/C12 -> 0.074915096
A13: 2372028 | B13: 4.3333333 | C13: =VLOOKUP(A13,'System Efficiency'!$A$4:$I$71,9,0) -> 19760 | D13: =VLOOKUP(A13,'System Efficiency'!$W$4:$AE$71,9,0) -> 5107 | E13: =D13/C13 -> 0.25845142
... A21: 2372902 | B21: 4.3333333 | C21: =VLOOKUP(A21,'System Efficiency'!$A$4:$I$71,9,0) -> 9770 | D21: =VLOOKUP(A21,'System Efficiency'!$W$4:$AE$71,9,0) -> 2201 | E21: =D21/C21 -> 0.22528147
A22: 2472001 | B22: 4.4545455 | C22: =VLOOKUP(A22,'System Efficiency'!$A$4:$I$71,9,0) -> 11619 | D22: =VLOOKUP(A22,'System Efficiency'!$W$4:$AE$71,9,0) -> 1790 | E22: =D22/C22 -> 0.15405801 | G22: Hasil regresi linear menunjukkan persamaan y = 0,0446x + 0,0218 dengan nilai R² sebesar 0,0716. Hal ini menunjukkan bahwa terdapat hubungan positif antara kualitas respons (verdict) dan rasio penggunaan token, di mana peningkatan kualitas cenderung diikuti oleh peningkatan penggunaan token. Namun, nilai R² yang rendah mengindikasikan bahwa pengaruh tersebut sangat lemah, sehingga kualitas respons bukan merupakan faktor utama yang menentukan efisiensi penggunaan token.
A23: 2472003 | B23: 4.5 | C23: =VLOOKUP(A23,'System Efficiency'!$A$4:$I$71,9,0) -> 3495 | D23: =VLOOKUP(A23,'System Efficiency'!$W$4:$AE$71,9,0) -> 652 | E23: =D23/C23 -> 0.18655222
A24: 2472005 | B24: 3 | C24: =VLOOKUP(A24,'System Efficiency'!$A$4:$I$71,9,0) -> 11945 | D24: =VLOOKUP(A24,'System Efficiency'!$W$4:$AE$71,9,0) -> 2784 | E24: =D24/C24 -> 0.23306823
A25: 2472007 | B25: 4.6666667 | C25: =VLOOKUP(A25,'System Efficiency'!$A$4:$I$71,9,0) -> 54678 | D25: =VLOOKUP(A25,'System Efficiency'!$W$4:$AE$71,9,0) -> 9652 | E25: =D25/C25 -> 0.17652438
A26: 2472008 | B26: 4.4285714 | C26: =VLOOKUP(A26,'System Efficiency'!$A$4:$I$71,9,0) -> 50674 | D26: =VLOOKUP(A26,'System Efficiency'!$W$4:$AE$71,9,0) -> 9825 | E26: =D26/C26 -> 0.19388641
A27: 2472009 | B27: 4 | C27: =VLOOKUP(A27,'System Efficiency'!$A$4:$I$71,9,0) -> 7816 | D27: =VLOOKUP(A27,'System Efficiency'!$W$4:$AE$71,9,0) -> 1149 | E27: =D27/C27 -> 0.14700614
A28: 2472010 | B28: 4.7272727 | C28: =VLOOKUP(A28,'System Efficiency'!$A$4:$I$71,9,0) -> 19286 | D28: =VLOOKUP(A28,'System Efficiency'!$W$4:$AE$71,9,0) -> 3710 | E28: =D28/C28 -> 0.19236752
A29: 2472011 | B29: 4.3333333 | C29: =VLOOKUP(A29,'System Efficiency'!$A$4:$I$71,9,0) -> 25683 | D29: =VLOOKUP(A29,'System Efficiency'!$W$4:$AE$71,9,0) -> 5204 | E29: =D29/C29 -> 0.2026243
A30: 2472012 | B30: 4.6666667 | C30: =VLOOKUP(A30,'System Efficiency'!$A$4:$I$71,9,0) -> 11923 | D30: =VLOOKUP(A30,'System Efficiency'!$W$4:$AE$71,9,0) -> 2097 | E30: =D30/C30 -> 0.17587855
A31: 2472013 | B31: 1 | C31: =VLOOKUP(A31,'System Efficiency'!$A$4:$I$71,9,0) -> 7674 | D31: =VLOOKUP(A31,'System Efficiency'!$W$4:$AE$71,9,0) -> 1145 | E31: =D31/C31 -> 0.14920511
A32: 2472014 | B32: 4.4 | C32: =VLOOKUP(A32,'System Efficiency'!$A$4:$I$71,9,0) -> 12235 | D32: =VLOOKUP(A32,'System Efficiency'!$W$4:$AE$71,9,0) -> 1732 | E32: =D32/C32 -> 0.1415611
A33: 2472017 | B33: 4.4 | C33: =VLOOKUP(A33,'System Efficiency'!$A$4:$I$71,9,0) -> 36963 | D33: =VLOOKUP(A33,'System Efficiency'!$W$4:$AE$71,9,0) -> 9702 | E33: =D33/C33 -> 0.26247869
A34: 2472018 | B34: 4.3333333 | C34: =VLOOKUP(A34,'System Efficiency'!$A$4:$I$71,9,0) -> 27513 | D34: =VLOOKUP(A34,'System Efficiency'!$W$4:$AE$71,9,0) -> 6519 | E34: =D34/C34 -> 0.23694254
... A66: 2472901 | B66: 3.6 | C66: =VLOOKUP(A66,'System Efficiency'!$A$4:$I$71,9,0) -> 8196 | D66: =VLOOKUP(A66,'System Efficiency'!$W$4:$AE$71,9,0) -> 504 | E66: =D66/C66 -> 0.061493411
